Metadata-Version: 2.1
Name: sh-py-mess-client
Version: 0.0.1
Summary: GeekBrains Mess Client. Coursework in a programming language.
Home-page: UNKNOWN
Author: Ivan Ivanov
Author-email: iv.iv@yandex.ru
License: UNKNOWN
Platform: UNKNOWN
Requires-Dist: PyQt5
Requires-Dist: sqlalchemy
Requires-Dist: pycryptodome
Requires-Dist: pycryptodomex
